[
    {
        "Артист": "Justin Timberlake",
        "Трек": "Mirrors",
        "Длительность(мс)": 484146,
        "Год": 2013,
        "Темп(?)": 76.899,
        "Жанр": "pop",
        "Громкость(?)": -6.664
    },
    {
        "Артист": "Nio Garcia",
        "Трек": "Te Boté - Remix",
        "Длительность(мс)": 417920,
        "Год": 2018,
        "Темп(?)": 96.507,
        "Жанр": "latin",
        "Громкость(?)": -3.445
    },
    {
        "Артист": "Lil' Kim",
        "Трек": "Magic Stick",
        "Длительность(мс)": 359973,
        "Год": 2019,
        "Темп(?)": 92.98,
        "Жанр": "hip hop, pop, R&B",
        "Громкость(?)": -7.872
    },
    {
        "Артист": "Daft Punk",
        "Трек": "Lose Yourself to Dance (feat. Pharrell Williams)",
        "Длительность(мс)": 353893,
        "Год": 2013,
        "Темп(?)": 100.163,
        "Жанр": "hip hop, Dance/Electronic",
        "Громкость(?)": -7.828
    },
    {
        "Артист": "Kendrick Lamar",
        "Трек": "m.A.A.d city",
        "Длительность(мс)": 350120,
        "Год": 2012,
        "Темп(?)": 91.048,
        "Жанр": "hip hop",
        "Громкость(?)": -6.815
    },
    {
        "Артист": "Migos",
        "Трек": "Bad and Boujee (feat. Lil Uzi Vert)",
        "Длительность(мс)": 343150,
        "Год": 2017,
        "Темп(?)": 127.079,
        "Жанр": "hip hop, pop",
        "Громкость(?)": -5.314
    },
    {
        "Артист": "JAY-Z",
        "Трек": "Holy Grail",
        "Длительность(мс)": 338413,
        "Год": 2013,
        "Темп(?)": 145.082,
        "Жанр": "hip hop",
        "Громкость(?)": -6.901
    },
    {
        "Артист": "Rae Sremmurd",
        "Трек": "Powerglide (feat. Juicy J) - From SR3MM",
        "Длительность(мс)": 332300,
        "Год": 2018,
        "Темп(?)": 173.948,
        "Жанр": "hip hop, pop",
        "Громкость(?)": -4.75
    },
    {
        "Артист": "Kanye West",
        "Трек": "Mercy",
        "Длительность(мс)": 329320,
        "Год": 2012,
        "Темп(?)": 139.993,
        "Жанр": "hip hop",
        "Громкость(?)": -9.381
    },
    {
        "Артист": "Justin Timberlake",
        "Трек": "Suit & Tie (feat. Jay-Z)",
        "Длительность(мс)": 326280,
        "Год": 2013,
        "Темп(?)": 101.985,
        "Жанр": "pop",
        "Громкость(?)": -3.799
    },
    {
        "Артист": "Beyoncé",
        "Трек": "Drunk in Love (feat. Jay-Z)",
        "Длительность(мс)": 323480,
        "Год": 2014,
        "Темп(?)": 140.03,
        "Жанр": "pop, R&B",
        "Громкость(?)": -6.902
    },
    {
        "Артист": "Lady Gaga",
        "Трек": "The Edge Of Glory",
        "Длительность(мс)": 320546,
        "Год": 2011,
        "Темп(?)": 127.952,
        "Жанр": "pop",
        "Громкость(?)": -6.477
    },
    {
        "Артист": "Kendrick Lamar",
        "Трек": "Swimming Pools (Drank) - Extended Version",
        "Длительность(мс)": 313786,
        "Год": 2012,
        "Темп(?)": 74.132,
        "Жанр": "hip hop",
        "Громкость(?)": -7.745
    },
    {
        "Артист": "Milky Chance",
        "Трек": "Stolen Dance",
        "Длительность(мс)": 313684,
        "Год": 2014,
        "Темп(?)": 114.016,
        "Жанр": "set()",
        "Громкость(?)": -8.813
    },
    {
        "Артист": "Future",
        "Трек": "Low Life (feat. The Weeknd)",
        "Длительность(мс)": 313546,
        "Год": 2016,
        "Темп(?)": 143.961,
        "Жанр": "hip hop, pop",
        "Громкость(?)": -7.789
    },
    {
        "Артист": "Travis Scott",
        "Трек": "SICKO MODE",
        "Длительность(мс)": 312820,
        "Год": 2018,
        "Темп(?)": 155.008,
        "Жанр": "hip hop, Dance/Electronic",
        "Громкость(?)": -3.714
    },
    {
        "Артист": "Travis Scott",
        "Трек": "SICKO MODE",
        "Длительность(мс)": 312820,
        "Год": 2018,
        "Темп(?)": 155.008,
        "Жанр": "hip hop, Dance/Electronic",
        "Громкость(?)": -3.714
    },
    {
        "Артист": "Migos",
        "Трек": "Slippery (feat. Gucci Mane)",
        "Длительность(мс)": 304041,
        "Год": 2017,
        "Темп(?)": 141.967,
        "Жанр": "hip hop, pop",
        "Громкость(?)": -5.661
    },
    {
        "Артист": "Bad Meets Evil",
        "Трек": "Lighters",
        "Длительность(мс)": 303813,
        "Год": 2011,
        "Темп(?)": 90.268,
        "Жанр": "hip hop, pop",
        "Громкость(?)": -8.327
    },
    {
        "Артист": "Migos",
        "Трек": "MotorSport",
        "Длительность(мс)": 303076,
        "Год": 2018,
        "Темп(?)": 137.996,
        "Жанр": "hip hop, pop",
        "Громкость(?)": -5.32
    },
    {
        "Артист": "Hugh Jackman",
        "Трек": "The Greatest Show",
        "Длительность(мс)": 302146,
        "Год": 2017,
        "Темп(?)": 157.92,
        "Жанр": "easy listening",
        "Громкость(?)": -7.36
    },
    {
        "Артист": "Anuel AA",
        "Трек": "China",
        "Длительность(мс)": 301714,
        "Год": 2019,
        "Темп(?)": 105.027,
        "Жанр": "latin",
        "Громкость(?)": -3.702
    },
    {
        "Артист": "Ed Sheeran",
        "Трек": "I See Fire - From \"The Hobbit - The Desolation Of Smaug\"",
        "Длительность(мс)": 300840,
        "Год": 2013,
        "Темп(?)": 152.037,
        "Жанр": "pop",
        "Громкость(?)": -20.514
    },
    {
        "Артист": "MGMT",
        "Трек": "Little Dark Age",
        "Длительность(мс)": 299960,
        "Год": 2018,
        "Темп(?)": 97.512,
        "Жанр": "rock",
        "Громкость(?)": -6.156
    },
    {
        "Артист": "ScHoolboy Q",
        "Трек": "Collard Greens",
        "Длительность(мс)": 299960,
        "Год": 2014,
        "Темп(?)": 153.972,
        "Жанр": "hip hop, pop",
        "Громкость(?)": -4.871
    },
    {
        "Артист": "Drake",
        "Трек": "Passionfruit",
        "Длительность(мс)": 298940,
        "Год": 2017,
        "Темп(?)": 111.98,
        "Жанр": "hip hop, pop, R&B",
        "Громкость(?)": -11.377
    },
    {
        "Артист": "DJ Khaled",
        "Трек": "I'm On One",
        "Длительность(мс)": 296146,
        "Год": 2011,
        "Темп(?)": 149.33,
        "Жанр": "hip hop, pop",
        "Громкость(?)": -3.499
    },
    {
        "Артист": "Adele",
        "Трек": "Hello",
        "Длительность(мс)": 295502,
        "Год": 2015,
        "Темп(?)": 157.98,
        "Жанр": "pop, R&B",
        "Громкость(?)": -6.129
    },
    {
        "Артист": "Nelly",
        "Трек": "Shake Ya Tailfeather (feat. P. Diddy & Murphy Lee) - 2016 Remaster",
        "Длительность(мс)": 293666,
        "Год": 2016,
        "Темп(?)": 87.025,
        "Жанр": "hip hop, pop, R&B",
        "Громкость(?)": -4.749
    },
    {
        "Артист": "Rudimental",
        "Трек": "Waiting All Night (feat. Ella Eyre)",
        "Длительность(мс)": 292586,
        "Год": 2013,
        "Темп(?)": 174.983,
        "Жанр": "pop, Dance/Electronic",
        "Громкость(?)": -5.358
    },
    {
        "Артист": "Rae Sremmurd",
        "Трек": "Black Beatles",
        "Длительность(мс)": 291893,
        "Год": 2016,
        "Темп(?)": 145.926,
        "Жанр": "hip hop, pop",
        "Громкость(?)": -6.163
    },
    {
        "Артист": "Lana Del Rey",
        "Трек": "Ride",
        "Длительность(мс)": 289080,
        "Год": 2012,
        "Темп(?)": 93.763,
        "Жанр": "pop",
        "Громкость(?)": -5.52
    },
    {
        "Артист": "21 Savage",
        "Трек": "a lot",
        "Длительность(мс)": 288624,
        "Год": 2018,
        "Темп(?)": 145.972,
        "Жанр": "hip hop",
        "Громкость(?)": -7.643
    },
    {
        "Артист": "Adele",
        "Трек": "Skyfall",
        "Длительность(мс)": 286480,
        "Год": 2012,
        "Темп(?)": 75.881,
        "Жанр": "pop, R&B",
        "Громкость(?)": -6.864
    },
    {
        "Артист": "Lana Del Rey",
        "Трек": "Born To Die",
        "Длительность(мс)": 286253,
        "Год": 2012,
        "Темп(?)": 75.223,
        "Жанр": "pop",
        "Громкость(?)": -6.591
    },
    {
        "Артист": "Duke Dumont",
        "Трек": "I Got U",
        "Длительность(мс)": 285596,
        "Год": 2014,
        "Темп(?)": 120.837,
        "Жанр": "pop, Dance/Electronic",
        "Громкость(?)": -7.752
    },
    {
        "Артист": "Adele",
        "Трек": "Someone Like You",
        "Длительность(мс)": 285240,
        "Год": 2011,
        "Темп(?)": 135.047,
        "Жанр": "pop, R&B",
        "Громкость(?)": -8.251
    },
    {
        "Артист": "Christina Perri",
        "Трек": "A Thousand Years",
        "Длительность(мс)": 285120,
        "Год": 2011,
        "Темп(?)": 139.028,
        "Жанр": "pop",
        "Громкость(?)": -7.445
    }
]